setup.cfg
setup.py
Flask_Dissect.egg-info/PKG-INFO
Flask_Dissect.egg-info/SOURCES.txt
Flask_Dissect.egg-info/dependency_links.txt
Flask_Dissect.egg-info/requires.txt
Flask_Dissect.egg-info/top_level.txt
flask_dissect/__init__.py
flask_dissect/dissect_exception.py
flask_dissect/session.py