Metadata-Version: 1.1
Name: Flask-Dissect
Version: 1.0.10
Summary: Dissect Distributed Session Control
Home-page: http://bit.epix.com.br/flask-dissect/
Author: Leandro Martelli
Author-email: martelli@epix.com.br
License: BSD
Platform: any
Classifier: Environment :: Web Environment
Classifier: Intended Audience :: Developers
Classifier: License :: OSI Approved :: BSD License
Classifier: Operating System :: OS Independent
Classifier: Programming Language :: Python
Classifier: Topic :: Software Development :: Libraries :: Python Modules
